HD_BET_minimal/__init__.py
HD_BET_minimal/config.py
HD_BET_minimal/data_loading.py
HD_BET_minimal/network_architecture.py
HD_BET_minimal/padorcut.py
HD_BET_minimal/predict_case.py
HD_BET_minimal/run.py
HD_BET_minimal/utils.py
HD_BET_minimal-1.0.dist-info/LICENSE
HD_BET_minimal-1.0.dist-info/METADATA
HD_BET_minimal-1.0.dist-info/WHEEL
HD_BET_minimal-1.0.dist-info/top_level.txt
HD_BET_minimal-1.0.dist-info/RECORD
