Metadata-Version: 2.1
Name: HD_BET-minimal
Version: 1.0
Summary: Tool for brain extraction
Home-page: https://github.com/dafne-imaging/dafne-HD-BET-minimal
Author: Fabian Isensee, Francesco Santini
Author-email: francesco.santini@unibas.ch
License: Apache 2.0
Classifier: Intended Audience :: Science/Research
Classifier: Programming Language :: Python
Classifier: Topic :: Scientific/Engineering
Classifier: Operating System :: Unix
Requires-Python: >=3.5
License-File: LICENSE
Requires-Dist: numpy
Requires-Dist: torch >=0.4.1
Requires-Dist: scikit-image
Requires-Dist: appdirs
Requires-Dist: requests
